{
    "ReportTemplate": "paged.html",
    "DataSource": "{{sampleLocation}}/jobs.json",
    "HeadersHtml": "<table style=\"border-collapse:collapse;width: 100%;\"><tbody>\n<tr>\n\t<td style=\"width: 20%;text-align:left;\">{{OrgAddress1}}<br/>{{OrgAddress2}}<br/>{{OrgAddress3}}</td>\n\t<td style=\"width: 60%; text-align: center;\"><strong>{{OrgTitle}}<br/>{{ReportTitle}}<br/>{{ReportSubTitle}}</strong><br></td>\n\t<td style=\"width: 20%;text-align:right;\">{@TodayDate('mm/dd/yyyy')@}</td></tr></tbody></table>",
    "FootersHtml": "<table style=\"border-collapse:collapse;width: 100%;\"><tbody>\n<tr>\n\t<td style=\"width: 20%;text-align:left;\">left footer line 1<br/>left footer line 2</td>\n\t<td style=\"width: 60%; text-align: center;\"><strong>{{Copyright}}</strong><br></td>\n\t<td style=\"width: 20%;text-align:right;\">right footer line 1</td></tr></tbody></table>",
    "Layout": {
        "PaperSize": "legal",
        "PaperLayout": "landscape",
        "Report-Top-Margin": "30",
        "Report-Right-Margin": "10",
        "Report-Bottom-Margin": "30",
        "Report-Left-Margin": "10"
    },
    "Columns": [
        {
            "displayName": "Instrument ID",
            "field": "InstrumentID"
        },
        {
            "displayName": "Instrument Date",
            "field": "InstrumentDate"
        },
        {
            "displayName": "Instrument Datehidden",
            "field": "InstrumentDatehidden"
        },
        {
            "displayName": "Date Indexed",
            "field": "DateIndexed"
        },
        {
            "displayName": "Book",
            "field": "Book"
        },
        {
            "displayName": "Volume",
            "field": "Volume"
        },
        {
            "displayName": "Page",
            "field": "Page"
        },
        {
            "displayName": "Act",
            "field": "Act"
        },
        {
            "displayName": "Kind",
            "field": "Kind"
        },
        {
            "displayName": "Index I D",
            "field": "IndexID"
        },
        {
            "displayName": "Index Name",
            "field": "IndexName"
        },
        {
            "displayName": "Value",
            "field": "Value"
        },
        {
            "displayName": "Is Submitted",
            "field": "isSubmitted"
        },
        {
            "displayName": "User Name",
            "field": "UserName"
        },
        {
            "displayName": "Section",
            "field": "Section"
        },
        {
            "displayName": "Township",
            "field": "Township"
        },
        {
            "displayName": "Range",
            "field": "Range"
        },
        {
            "displayName": "Direct Name",
            "field": "DirectName"
        },
        {
            "displayName": "Description",
            "field": "Description"
        },
        {
            "displayName": "Indirect Name",
            "field": "IndirectName"
        },
        {
            "displayName": "Compare",
            "field": "Compare"
        },
        {
            "displayName": "Street Number",
            "field": "StreetNumber"
        },
        {
            "displayName": "Street Name",
            "field": "StreetName"
        },
        {
            "displayName": "City",
            "field": "City"
        },
        {
            "displayName": "State",
            "field": "State"
        },
        {
            "displayName": "Zip",
            "field": "Zip"
        },
        {
            "displayName": "Internet Image",
            "field": "InternetImage"
        },
        {
            "displayName": "Intranet Image",
            "field": "IntranetImage"
        },
        {
            "displayName": "Related Doc Flag",
            "field": "RelatedDocFlag"
        },
        {
            "displayName": "Instrument Date As String",
            "field": "InstrumentDateAsString"
        },
        {
            "displayName": "Instrument Date As Date Time",
            "field": "InstrumentDateAsDateTime"
        }
    ]
}